{
  "subcategory": [
    {
      "id": "1",
      "category_id": 1735548932028,
      "name": "Subcategory 1",
      "description": "Description 1"
    },
    {
      "id": "1736739962017",
      "category_id": 1735699054658,
      "name": "new oml",
      "description": "nvisinoi iw"
    },
    {
      "id": "1736880787835",
      "category_id": 1735699054658,
      "name": "two is awesomr",
      "description": "njs jnjnndj"
    },
    {
      "id": "8f00",
      "category_id": 1735548932028,
      "name": "new  okokok",
      "description": "okokok"
    },
    {
      "id": "ea68",
      "category_id": 1735699054658,
      "name": "baucbiu usbvui",
      "description": "nuisbv nsuvus"
    },
    {
      "id": "12b3",
      "category_id": 1735706070845,
      "name": "new oko oko",
      "description": "kokokokokokoo"
    }
  ]
}